cgn_ec_rust_parsers-0.2.0.dist-info/METADATA
cgn_ec_rust_parsers-0.2.0.dist-info/WHEEL
cgn_ec_rust_parsers/__init__.py
cgn_ec_rust_parsers/cgn_ec_rust_parsers.cpython-312-x86_64-linux-gnu.so
cgn_ec_rust_parsers-0.2.0.dist-info/RECORD
