Metadata-Version: 2.4
Name: cgn_ec_rust_parsers
Version: 0.2.0
